[
{
    "pk": 1, 
    "model": "staff.privilegios", 
    "fields": {
        "nombre": "Gerencia", 
        "valor": 1
    }
},
{
    "pk": 2, 
    "model": "staff.privilegios", 
    "fields": {
        "nombre": "Comunicacion", 
        "valor": 2
    }
},
{
    "pk": 3, 
    "model": "staff.privilegios", 
    "fields": {
        "nombre": "Edicion", 
        "valor": 3
    }
},
{
    "pk": 4, 
    "model": "staff.privilegios", 
    "fields": {
        "nombre": "Logistica", 
        "valor": 4
    }
},
{
    "pk": 5, 
    "model": "staff.privilegios", 
    "fields": {
        "nombre": "Administracion", 
        "valor": 5
    }
},
{
    "pk": 8, 
    "model": "staff.privilegios", 
    "fields": {
        "nombre": "Camarografo", 
        "valor": 6
    }
},
{
    "pk": 1, 
    "model": "staff.equipos", 
    "fields": {
        "flash": null, 
        "marca": null, 
        "lente_2": null, 
        "lente_3": null, 
        "lente_1": null, 
        "otros": null, 
        "memorias": null, 
        "iluminacion": null
    }
},
{
    "pk": 1, 
    "model": "staff.experiencia", 
    "fields": {
        "tipos": null, 
        "photoshop": null, 
        "lightroom": null
    }
},
{
    "pk": 1, 
    "model": "staff.datodepago", 
    "fields": {
        "banco": null, 
        "tipo_de_cuenta": null, 
        "numero": null
    }
},
{
    "pk": 2, 
    "model": "staff.usuario", 
    "fields": {
        "telefono_otro": "", 
        "equipos": 1, 
        "apellido": "Nori", 
        "usuario": 1, 
        "twitter": "", 
        "experiencia": 1, 
        "telefono_fijo": "58212751697", 
        "privilegio": 1, 
        "datos_pago": 1, 
        "nombre": "Franco", 
        "email": "francong2@gmail.com", 
        "cedula": "18740151", 
        "telefono_celular": ""
    }
},
{
    "pk": 4, 
    "model": "staff.staffporfuncion", 
    "fields": {
        "bloque": null, 
        "cantidad": 0, 
        "tipo": 8, 
        "funcion": 2
    }
},
{
    "pk": 5, 
    "model": "staff.staffporfuncion", 
    "fields": {
        "bloque": 1, 
        "cantidad": 1, 
        "tipo": 8, 
        "funcion": 2
    }
}
]